docutils/__init__.py
docutils/_compat.py
docutils/core.py
docutils/examples.py
docutils/frontend.py
docutils/io.py
docutils/nodes.py
docutils/statemachine.py
docutils/languages/__init__.py
docutils/languages/af.py
docutils/languages/ca.py
docutils/languages/cs.py
docutils/languages/da.py
docutils/languages/de.py
docutils/languages/en.py
docutils/languages/eo.py
docutils/languages/es.py
docutils/languages/fa.py
docutils/languages/fi.py
docutils/languages/fr.py
docutils/languages/gl.py
docutils/languages/he.py
docutils/languages/it.py
docutils/languages/ja.py
docutils/languages/ko.py
docutils/languages/lt.py
docutils/languages/lv.py
docutils/languages/nl.py
docutils/languages/pl.py
docutils/languages/pt_br.py
docutils/languages/ru.py
docutils/languages/sk.py
docutils/languages/sv.py
docutils/languages/zh_cn.py
docutils/languages/zh_tw.py
docutils/parsers/__init__.py
docutils/parsers/null.py
docutils/parsers/rst/__init__.py
docutils/parsers/rst/roles.py
docutils/parsers/rst/states.py
docutils/parsers/rst/tableparser.py
docutils/parsers/rst/directives/__init__.py
docutils/parsers/rst/directives/admonitions.py
docutils/parsers/rst/directives/body.py
docutils/parsers/rst/directives/html.py
docutils/parsers/rst/directives/images.py
docutils/parsers/rst/directives/misc.py
docutils/parsers/rst/directives/parts.py
docutils/parsers/rst/directives/references.py
docutils/parsers/rst/directives/tables.py
docutils/parsers/rst/include/README.txt
docutils/parsers/rst/include/isoamsa.txt
docutils/parsers/rst/include/isoamsb.txt
docutils/parsers/rst/include/isoamsc.txt
docutils/parsers/rst/include/isoamsn.txt
docutils/parsers/rst/include/isoamso.txt
docutils/parsers/rst/include/isoamsr.txt
docutils/parsers/rst/include/isobox.txt
docutils/parsers/rst/include/isocyr1.txt
docutils/parsers/rst/include/isocyr2.txt
docutils/parsers/rst/include/isodia.txt
docutils/parsers/rst/include/isogrk1.txt
docutils-0.15.dist-info/DESCRIPTION.rst
docutils-0.15.dist-info/METADATA
docutils-0.15.dist-info/RECORD
docutils-0.15.dist-info/WHEEL
docutils-0.15.dist-info/metadata.json
docutils-0.15.dist-info/top_level.txt
